nestbox_ai_functions/__init__.py
nestbox_ai_functions/agent/__init__.py
nestbox_ai_functions/agent/init.py
nestbox_ai_functions/agent/use_agent.py
nestbox_ai_functions/chatbot/__init__.py
nestbox_ai_functions/chatbot/init.py
nestbox_ai_functions/chatbot/use_chatbot.py
nestbox_ai_functions/common/__init__.py
nestbox_ai_functions/common/event_configs.py
nestbox_ai_functions/common/grpc_client.py
nestbox_ai_functions/common/stream_manager.py
nestbox_ai_functions/types/__init__.py
nestbox_ai_functions/types/agent/__init__.py
nestbox_ai_functions/types/agent/context.py
nestbox_ai_functions/types/agent/events.py
nestbox_ai_functions/types/agent/handler.py
nestbox_ai_functions/types/agent/payload.py
nestbox_ai_functions/types/chatbot/__init__.py
nestbox_ai_functions/types/chatbot/context.py
nestbox_ai_functions/types/chatbot/events.py
nestbox_ai_functions/types/chatbot/handler.py
nestbox_ai_functions/types/chatbot/message.py
nestbox_ai_functions/types/chatbot/payload.py
nestbox_ai_functions-2.0.3.dist-info/METADATA
nestbox_ai_functions-2.0.3.dist-info/WHEEL
nestbox_ai_functions-2.0.3.dist-info/top_level.txt
nestbox_ai_functions-2.0.3.dist-info/RECORD
