Metadata-Version: 2.4
Name: nestbox-ai-functions
Version: 2.0.3
Summary: Python equivalent of Nestbox agent module
Requires-Dist: grpcio>=1.56.0
Requires-Dist: protobuf>=4.21.0
